libspeech/__init__.py
libspeech/__main__.py
libspeech/_about.cpython-311-x86_64-linux-gnu.so
libspeech/_audio.cpython-311-x86_64-linux-gnu.so
libspeech/core.py
libspeech/libaudioflux.so
libspeech/libonnxruntime.so.1.21.0
libspeech/libspeech.so
libspeech-0.0.0.dist-info/METADATA
libspeech-0.0.0.dist-info/WHEEL
libspeech-0.0.0.dist-info/entry_points.txt
libspeech-0.0.0.dist-info/licenses/LICENSE
libspeech-0.0.0.dist-info/RECORD
